kraken_localize/__init__.py
kraken_localize/class_kraken_localize.py
kraken_localize/kraken_localize.py
kraken_localize/helpers/__init__.py
kraken_localize/helpers/json.py
kraken_localize/helpers/things.py
kraken_localize/localizations/__init__.py
kraken_localize/localizations/currency.py
kraken_localize/localizations/date.py
kraken_localize/localizations/number.py
kraken_localize/localizations/text.py
kraken_localize-0.0.16.dist-info/LICENSE.txt
kraken_localize-0.0.16.dist-info/METADATA
kraken_localize-0.0.16.dist-info/WHEEL
kraken_localize-0.0.16.dist-info/top_level.txt
kraken_localize-0.0.16.dist-info/RECORD
